tvmaze/__init__.py
tvmaze/api.py
tvmaze/character.py
tvmaze/client.py
tvmaze/episode.py
tvmaze/expections.py
tvmaze/models.py
tvmaze/network.py
tvmaze/people.py
tvmaze/schedule.py
tvmaze/search.py
tvmaze/show.py
tvmaze/webchannel.py
python_tvmaze-1.0.5.dist-info/LICENSE
python_tvmaze-1.0.5.dist-info/METADATA
python_tvmaze-1.0.5.dist-info/WHEEL
python_tvmaze-1.0.5.dist-info/top_level.txt
python_tvmaze-1.0.5.dist-info/zip-safe
python_tvmaze-1.0.5.dist-info/RECORD
